Metadata-Version: 2.1
Name: odoo12-addon-account-analytic-sequence
Version: 12.0.1.1.0
Summary: Restore the analytic account sequence
Home-page: https://github.com/OCA/account-analytic
Author: ACSONE SA/NV,Odoo Community Association (OCA)
Author-email: support@odoo-community.org
License: AGPL-3
Platform: UNKNOWN
Classifier: Programming Language :: Python
Classifier: Framework :: Odoo
Classifier: License :: OSI Approved :: GNU Affero General Public License v3
Requires-Python: >=3.5
Requires-Dist: odoo (<12.1dev,>=12.0a)
